[
  {
    "SD_CD": "11",
    "SD_NM": "서울특별시",
    "PM2_5_min": 27.38791749,
    "PM2_5_max": 30.31247428,
    "PM10_min": 40.28569786,
    "PM10_max": 45.47693198,
    "NO2_min": 27.15855278,
    "NO2_max": 38.13786386
  },
  {
    "SD_CD": "21",
    "SD_NM": "부산광역시",
    "PM2_5_min": 31.44080509,
    "PM2_5_max": 40.49745307,
    "PM10_min": 38.95408945,
    "PM10_max": 49.68658302,
    "NO2_min": 18.71758898,
    "NO2_max": 24.45983748
  },
  {
    "SD_CD": "22",
    "SD_NM": "대구광역시",
    "PM2_5_min": 33.9582115,
    "PM2_5_max": 36.97833243,
    "PM10_min": 39.0443199,
    "PM10_max": 41.80166103,
    "NO2_min": 18.52970315,
    "NO2_max": 21.97517149
  },
  {
    "SD_CD": "31",
    "SD_NM": "경기도",
    "PM2_5_min": 27.76112184,
    "PM2_5_max": 46.64152108,
    "PM10_min": 40.2024369,
    "PM10_max": 55.55302552,
    "NO2_min": 9.786058175,
    "NO2_max": 38.31604405
  },
  {
    "SD_CD": "23",
    "SD_NM": "인천광역시",
    "PM2_5_min": 25.52235226,
    "PM2_5_max": 32.60927307,
    "PM10_min": 34.56477404,
    "PM10_max": 48.12335909,
    "NO2_min": 6.604139721,
    "NO2_max": 33.9083614
  },
  {
    "SD_CD": "24",
    "SD_NM": "광주광역시",
    "PM2_5_min": 29.36974891,
    "PM2_5_max": 35.90659028,
    "PM10_min": 34.42736778,
    "PM10_max": 43.06947492,
    "NO2_min": 14.61360511,
    "NO2_max": 19.28606735
  },
  {
    "SD_CD": "25",
    "SD_NM": "대전광역시",
    "PM2_5_min": 33.97817817,
    "PM2_5_max": 37.22742113,
    "PM10_min": 39.10760485,
    "PM10_max": 42.34971249,
    "NO2_min": 19.84417069,
    "NO2_max": 22.47734537
  },
  {
    "SD_CD": "26",
    "SD_NM": "울산광역시",
    "PM2_5_min": 35.52960406,
    "PM2_5_max": 39.23595664,
    "PM10_min": 41.10975112,
    "PM10_max": 46.05709764,
    "NO2_min": 19.99611963,
    "NO2_max": 26.04903564
  },
  {
    "SD_CD": "29",
    "SD_NM": "세종특별자치시",
    "PM2_5_min": 38.56377195,
    "PM2_5_max": 38.56377195,
    "PM10_min": 44.18473076,
    "PM10_max": 44.18473076,
    "NO2_min": 18.20878043,
    "NO2_max": 18.20878043
  },
  {
    "SD_CD": "32",
    "SD_NM": "강원도",
    "PM2_5_min": 21.79571779,
    "PM2_5_max": 41.7925881,
    "PM10_min": 25.91999712,
    "PM10_max": 51.20964992,
    "NO2_min": 3.842632089,
    "NO2_max": 16.92356914
  },
  {
    "SD_CD": "33",
    "SD_NM": "충청북도",
    "PM2_5_min": 32.51571985,
    "PM2_5_max": 43.38676108,
    "PM10_min": 36.31224115,
    "PM10_max": 50.88156185,
    "NO2_min": 11.9562927,
    "NO2_max": 23.80998375
  },
  {
    "SD_CD": "34",
    "SD_NM": "충청남도",
    "PM2_5_min": 27.22542925,
    "PM2_5_max": 39.86254312,
    "PM10_min": 35.2770423,
    "PM10_max": 46.40462485,
    "NO2_min": 9.238663283,
    "NO2_max": 19.76724291
  },
  {
    "SD_CD": "35",
    "SD_NM": "전라북도",
    "PM2_5_min": 27.49538102,
    "PM2_5_max": 43.78911839,
    "PM10_min": 30.78476286,
    "PM10_max": 50.17190423,
    "NO2_min": 8.483736766,
    "NO2_max": 19.18854795
  },
  {
    "SD_CD": "36",
    "SD_NM": "전라남도",
    "PM2_5_min": 17.12958203,
    "PM2_5_max": 37.04133557,
    "PM10_min": 25.44839236,
    "PM10_max": 43.10878065,
    "NO2_min": 4.11436457,
    "NO2_max": 19.45061221
  },
  {
    "SD_CD": "37",
    "SD_NM": "경상북도",
    "PM2_5_min": 7.708982966,
    "PM2_5_max": 41.15121767,
    "PM10_min": 15.22931352,
    "PM10_max": 49.03696017,
    "NO2_min": 0.508889193,
    "NO2_max": 20.73510946
  },
  {
    "SD_CD": "38",
    "SD_NM": "경상남도",
    "PM2_5_min": 26.99731416,
    "PM2_5_max": 37.9677849,
    "PM10_min": 33.58222769,
    "PM10_max": 43.85743329,
    "NO2_min": 7.354117219,
    "NO2_max": 18.34478734
  },
  {
    "SD_CD": "39",
    "SD_NM": "제주특별자치도",
    "PM2_5_min": 13.3007452,
    "PM2_5_max": 13.37231895,
    "PM10_min": 18.08178486,
    "PM10_max": 18.62510808,
    "NO2_min": 3.852801347,
    "NO2_max": 4.032448236
  }
]